labelsig/__init__.py
labelsig/__main__.py
labelsig/config/Annotation_multilabel.config
labelsig/config/Annotation_singlelabel.config
labelsig/config/LabelSIG.bat
labelsig/config/__init__.py
labelsig/config/create_batch_file.py
labelsig/config/history.config
labelsig/resource/WindowIcon.ico
labelsig/resource/WindowIcon.png
labelsig/resource/close.png
labelsig/resource/fixed.png
labelsig/resource/lock.png
labelsig/resource/logo.ico
labelsig/resource/max.png
labelsig/resource/min.png
labelsig/resource/set.png
"labelsig/resource/square-format,-transparent-background-designify.png"
labelsig/ui_designs/ui_fault_detection_view.ui
labelsig/ui_designs/ui_fault_identification_view.ui
labelsig/ui_designs/ui_fault_localization_view.ui
labelsig/ui_designs/ui_label_management_view.ui
labelsig/ui_designs/ui_main_view.ui
labelsig/ui_generated/__init__.py
labelsig/ui_generated/ui_fault_detection_view.py
labelsig/ui_generated/ui_fault_identification_view.py
labelsig/ui_generated/ui_fault_localization_view.py
labelsig/ui_generated/ui_label_management_view.py
labelsig/ui_generated/ui_main_view.py
labelsig/utils/Comtrade.py
labelsig/utils/__init__.py
labelsig/utils/utils_annotation.py
labelsig/utils/utils_comtrade.py
labelsig/utils/utils_datasets.py
labelsig/utils/utils_general.py
labelsig/widget/ChannelSelectionView.py
labelsig/widget/CountdownWarningView.py
labelsig/widget/FaultDetectionView.py
labelsig/widget/FaultIdentificationView.py
labelsig/widget/FaultLocalizationView.py
labelsig/widget/HelpView.py
labelsig/widget/LabelManagementView.py
labelsig/widget/MainView.py
labelsig/widget/WaveformVisualizerView.py
labelsig/widget/__init__.py
LabelSIG-2.0.9.dist-info/METADATA
LabelSIG-2.0.9.dist-info/WHEEL
LabelSIG-2.0.9.dist-info/entry_points.txt
LabelSIG-2.0.9.dist-info/top_level.txt
LabelSIG-2.0.9.dist-info/RECORD
