Metadata-Version: 2.1
Name: LabelSIG
Version: 2.0.9
Summary: Signal Labeling with Python
Home-page: https://github.com/Jianhong-Gao/LabelSIG
Author: Jianhong Gao
Author-email: gaojianhong1994@foxmail.com
License: MIT
Keywords: Signal Labeling,Machine Learning
Classifier: Development Status :: 5 - Production/Stable
Classifier: Intended Audience :: Developers
Classifier: Intended Audience :: Science/Research
Classifier: Natural Language :: English
Classifier: Operating System :: OS Independent
Classifier: Programming Language :: Python
Classifier: Programming Language :: Python :: 3.9
Classifier: Programming Language :: Python :: 3 :: Only
Requires-Python: >=3.9
Requires-Dist: numpy ==1.26.1
Requires-Dist: PyQt5 ==5.15.11
Requires-Dist: PyQt5-sip ==12.15.0
Requires-Dist: pywin32 ==306
Requires-Dist: QtPy ==2.4.1
